Lab_09/Ejer3/FlipFlopJK.v
// FlipFlop tipo JK

module FF1b(
  input wire clk, enable, reset,
  input wire D,
  output reg Q);

  always @(posedge clk or posedge reset) begin
    if(reset)
      Q <= 0;
    else if(enable)
      Q <= D;
  end
endmodule

module FFJK(
  input wire clk, reset, enable, J, K,
  output wire Q);

    wire nQ, nK, aJ, ak, q;

    not(nQ, Q);
    not(nK, K);
    and(aJ, J, nQ);
    and(aK, nK, Q);
    or(q, aJ, aK);

    FF1b u(clk, reset, enable, Q, q);
endmodule

Lab_09/Ejer3/FlipFlopJK_tb.v
module testbench();

reg clk, reset, enable, J, K;
wire Q;

FFJK a(clk, reset, enable, J, K, Q);

always
  #2 clk = ~clk;

initial begin
  #1
  $display("-------------------------------");
  $display("clk | reset | enable | J | K || Q ");
  $display("------------------||------------");
  $monitor("%b  %b  %b  %b  %b ||  %b", clk, reset, enable, J, K, Q);
  reset=0; clk=0; enable=0; J=0; K=0;
  #2 reset = 0;
  #2 reset = 1;
  #2 reset = 0;
  #2 enable = 1; J = 1;
  #2 enable = 0;
  #2 enable = 1; J = 0;
  #2 K = 1;
  #2 K = 0; J = 1;
  #2 K = 1;
end

initial
  #20 $finish;
initial begin
  $dumpfile("FlipFlopJK_tb.vcd");
  $dumpvars(0, testbench);
end

endmodule

Lab_09/Ejer3/FlipFlopJK_tb.vcd
$date
	Sat Oct 31 11:40:32 2020
$end
$version
	Icarus Verilog
$end
$timescale
	1ps
$end
$scope module testbench $end
$var wire 1 ! Q $end
$var reg 1 " J $end
$var reg 1 # K $end
$var reg 1 $ clk $end
$var reg 1 % enable $end
$var reg 1 & reset $end
$scope module a $end
$var wire 1 " J $end
$var wire 1 # K $end
$var wire 1 ! Q $end
$var wire 1 ' aJ $end
$var wire 1 ( aK $end
$var wire 1 $ clk $end
$var wire 1 % enable $end
$var wire 1 ) nK $end
$var wire 1 * nQ $end
$var wire 1 + q $end
$var wire 1 & reset $end
$scope module u $end
$var wire 1 ! D $end
$var wire 1 $ clk $end
$var wire 1 & enable $end
$var wire 1 % reset $end
$var reg 1 , Q $end
$upscope $end
$upscope $end
$upscope $end
$enddefinitions $end
#0
$dumpvars
x,
x+
z*
x)
x(
x'
x&
x%
x$
x#
x"
z!
$end
#1
1)
0'
0#
0"
0%
0$
0&
#2
1$
#4
0$
#5
1&
#6
z,
1$
#7
0&
#8
0$
#9
0,
x'
1"
1%
#10
1$
#11
0%
#12
0$
#13
0'
0"
1%
#14
1$
#15
0+
0(
0)
1#
#16
0$
#17
x+
x(
x'
1)
1"
0#
#18
1$
#19
0(
0)
1#
